[{"Yaş Grubu":" 18-24 "," Kadın Seçmen Sayısı ":"203.155"," Erkek Seçmen Sayısı ":"224.627"," Toplam ":"427.782"},{"Yaş Grubu":" 25-29 "," Kadın Seçmen Sayısı ":"144.824"," Erkek Seçmen Sayısı ":"176.025"," Toplam ":"320.849"},{"Yaş Grubu":" 30-34 "," Kadın Seçmen Sayısı ":"158.967"," Erkek Seçmen Sayısı ":"186.493"," Toplam ":"345.460"},{"Yaş Grubu":" 35-39 "," Kadın Seçmen Sayısı ":"179.210"," Erkek Seçmen Sayısı ":"209.396"," Toplam ":"388.606"},{"Yaş Grubu":" 40-44 "," Kadın Seçmen Sayısı ":"183.681"," Erkek Seçmen Sayısı ":"195.336"," Toplam ":"379.017"},{"Yaş Grubu":" 45-49 "," Kadın Seçmen Sayısı ":"144.361"," Erkek Seçmen Sayısı ":"168.272"," Toplam ":"312.633"},{"Yaş Grubu":" 50-54 "," Kadın Seçmen Sayısı ":"109.237"," Erkek Seçmen Sayısı ":"141.862"," Toplam ":"251.099"},{"Yaş Grubu":" 55-59 "," Kadın Seçmen Sayısı ":"67.986"," Erkek Seçmen Sayısı ":"82.616"," Toplam ":"150.602"},{"Yaş Grubu":" 60-64 "," Kadın Seçmen Sayısı ":"54.926"," Erkek Seçmen Sayısı ":"45.255"," Toplam ":"100.181"},{"Yaş Grubu":" 65-69 "," Kadın Seçmen Sayısı ":"50.011"," Erkek Seçmen Sayısı ":"41.011"," Toplam ":"91.022"},{"Yaş Grubu":" 70-74 "," Kadın Seçmen Sayısı ":"31.953"," Erkek Seçmen Sayısı ":"33.593"," Toplam ":"65.546"},{"Yaş Grubu":" 75+ "," Kadın Seçmen Sayısı ":"32.824"," Erkek Seçmen Sayısı ":"33.448"," Toplam ":"66.272"}]