[{"İl Kodu":"","İl Adı":"ADANA","Siyasi Parti Adı":" CUMHURİYET HALK PARTİSİ ","Adı Soyadı":"ZEYDAN KARALAR"},{"İl Kodu":"","İl Adı":"ANKARA","Siyasi Parti Adı":" CUMHURİYET HALK PARTİSİ ","Adı Soyadı":"MANSUR YAVAŞ"},{"İl Kodu":"","İl Adı":"ANTALYA","Siyasi Parti Adı":" CUMHURİYET HALK PARTİSİ ","Adı Soyadı":"MUHİTTİN BÖCEK"},{"İl Kodu":"","İl Adı":"AYDIN","Siyasi Parti Adı":" CUMHURİYET HALK PARTİSİ ","Adı Soyadı":"ÖZLEM ÇERÇİOĞLU"},{"İl Kodu":"","İl Adı":"BALIKESİR","Siyasi Parti Adı":" CUMHURİYET HALK PARTİSİ ","Adı Soyadı":"AHMET AKIN"},{"İl Kodu":"","İl Adı":"BURSA","Siyasi Parti Adı":" CUMHURİYET HALK PARTİSİ ","Adı Soyadı":"MUSTAFA BOZBEY"},{"İl Kodu":"","İl Adı":"DENİZLİ","Siyasi Parti Adı":" CUMHURİYET HALK PARTİSİ ","Adı Soyadı":"BÜLENT NURİ ÇAVUŞOĞLU"},{"İl Kodu":"","İl Adı":"DİYARBAKIR","Siyasi Parti Adı":" HALKLARIN EŞİTLİK VE DEMOKRASİ PARTİSİ ","Adı Soyadı":"AYŞE SERRA BUCAK KÜÇÜK"},{"İl Kodu":"","İl Adı":"ERZURUM","Siyasi Parti Adı":" ADALET VE KALKINMA PARTİSİ ","Adı Soyadı":"MEHMET SEKMEN"},{"İl Kodu":"","İl Adı":"ESKİŞEHİR","Siyasi Parti Adı":" CUMHURİYET HALK PARTİSİ ","Adı Soyadı":"AYŞE ÜNLÜCE"},{"İl Kodu":"","İl Adı":"GAZİANTEP","Siyasi Parti Adı":" ADALET VE KALKINMA PARTİSİ ","Adı Soyadı":"FATMA ŞAHİN"},{"İl Kodu":"","İl Adı":"HATAY","Siyasi Parti Adı":" ADALET VE KALKINMA PARTİSİ ","Adı Soyadı":"MEHMET ÖNTÜRK"},{"İl Kodu":"","İl Adı":"MERSİN","Siyasi Parti Adı":" CUMHURİYET HALK PARTİSİ ","Adı Soyadı":"VAHAP SEÇER"},{"İl Kodu":"","İl Adı":"İSTANBUL","Siyasi Parti Adı":" CUMHURİYET HALK PARTİSİ ","Adı Soyadı":"EKREM İMAMOĞLU"},{"İl Kodu":"","İl Adı":"İZMİR","Siyasi Parti Adı":" CUMHURİYET HALK PARTİSİ ","Adı Soyadı":"CEMİL TUGAY"},{"İl Kodu":"","İl Adı":"KAYSERİ","Siyasi Parti Adı":" ADALET VE KALKINMA PARTİSİ ","Adı Soyadı":"MEMDUH BÜYÜKKILIÇ"},{"İl Kodu":"","İl Adı":"KOCAELİ","Siyasi Parti Adı":" ADALET VE KALKINMA PARTİSİ ","Adı Soyadı":"TAHİR BÜYÜKAKIN"},{"İl Kodu":"","İl Adı":"KONYA","Siyasi Parti Adı":" ADALET VE KALKINMA PARTİSİ ","Adı Soyadı":"UĞUR İBRAHİM ALTAY"},{"İl Kodu":"","İl Adı":"MALATYA","Siyasi Parti Adı":" ADALET VE KALKINMA PARTİSİ ","Adı Soyadı":"SAMİ ER"},{"İl Kodu":"","İl Adı":"MANİSA","Siyasi Parti Adı":" CUMHURİYET HALK PARTİSİ ","Adı Soyadı":"FERDİ ZEYREK"},{"İl Kodu":"","İl Adı":"KAHRAMANMARAŞ","Siyasi Parti Adı":" ADALET VE KALKINMA PARTİSİ ","Adı Soyadı":"FIRAT GÖRGEL"},{"İl Kodu":"","İl Adı":"MARDİN","Siyasi Parti Adı":" HALKLARIN EŞİTLİK VE DEMOKRASİ PARTİSİ ","Adı Soyadı":"AHMET TÜRK"},{"İl Kodu":"","İl Adı":"MUĞLA","Siyasi Parti Adı":" CUMHURİYET HALK PARTİSİ ","Adı Soyadı":"AHMET ARAS"},{"İl Kodu":"","İl Adı":"ORDU","Siyasi Parti Adı":" ADALET VE KALKINMA PARTİSİ ","Adı Soyadı":"MEHMET HİLMİ GÜLER"},{"İl Kodu":"","İl Adı":"SAKARYA","Siyasi Parti Adı":" ADALET VE KALKINMA PARTİSİ ","Adı Soyadı":"YUSUF ALEMDAR"},{"İl Kodu":"","İl Adı":"SAMSUN","Siyasi Parti Adı":" ADALET VE KALKINMA PARTİSİ ","Adı Soyadı":"HALİT DOĞAN"},{"İl Kodu":"","İl Adı":"TEKİRDAĞ","Siyasi Parti Adı":" CUMHURİYET HALK PARTİSİ ","Adı Soyadı":"CANDAN YÜCEER"},{"İl Kodu":"","İl Adı":"TRABZON","Siyasi Parti Adı":" ADALET VE KALKINMA PARTİSİ ","Adı Soyadı":"AHMET METİN GENÇ"},{"İl Kodu":"","İl Adı":"ŞANLIURFA","Siyasi Parti Adı":" YENİDEN REFAH PARTİSİ ","Adı Soyadı":"MEHMET KASIM GÜLPINAR"},{"İl Kodu":"","İl Adı":"VAN","Siyasi Parti Adı":" HALKLARIN EŞİTLİK VE DEMOKRASİ PARTİSİ ","Adı Soyadı":"ABDULLAH ZEYDAN"}]